LICENSE
README.md
setup.py
test/test_utoken.py
utoken/__init__.py
utoken/exceptions.py
utoken/utoken.py
utokeniz.egg-info/PKG-INFO
utokeniz.egg-info/SOURCES.txt
utokeniz.egg-info/dependency_links.txt
utokeniz.egg-info/top_level.txt