Metadata-Version: 2.1
Name: utokeniz
Version: 2.0.1
Summary: Create healthy and secure authentication tokens with UTokeniz.
Home-page: https://github.com/jaedsonpys/utoken
Author: Jaedson Silva
Author-email: imunknowuser@protonmail.com
License: BSD-3-Clause
Keywords: token,auth,json,web,login,secure
Platform: UNKNOWN
License-File: LICENSE
